README.rst
setup.cfg
setup.py
okta/AppInstanceClient.py
okta/AuthClient.py
okta/EventsClient.py
okta/FactorsAdminClient.py
okta/FactorsClient.py
okta/SessionsClient.py
okta/UserGroupsClient.py
okta/UsersClient.py
okta/__init__.py
okta/framework/ApiClient.py
okta/framework/Deserializer.py
okta/framework/OktaError.py
okta/framework/PagedResults.py
okta/framework/Serializer.py
okta/framework/Utils.py
okta/framework/__init__.py
okta/models/Embedded.py
okta/models/Link.py
okta/models/__init__.py
okta/models/app/Accessibility.py
okta/models/app/AppCredentials.py
okta/models/app/AppGroup.py
okta/models/app/AppInstance.py
okta/models/app/AppLinks.py
okta/models/app/AppSettings.py
okta/models/app/AppUser.py
okta/models/app/AppUserCredentials.py
okta/models/app/AppUserProfile.py
okta/models/app/Hide.py
okta/models/app/Settings.py
okta/models/app/UserNameTemplate.py
okta/models/app/Visibility.py
okta/models/app/__init__.py
okta/models/auth/AuthResult.py
okta/models/auth/__init__.py
okta/models/event/Action.py
okta/models/event/Actor.py
okta/models/event/Event.py
okta/models/event/Target.py
okta/models/event/__init__.py
okta/models/factor/Factor.py
okta/models/factor/FactorCatalogEntry.py
okta/models/factor/FactorDevice.py
okta/models/factor/FactorDeviceEnrollRequest.py
okta/models/factor/FactorDeviceRequest.py
okta/models/factor/FactorEnrollRequest.py
okta/models/factor/FactorProfile.py
okta/models/factor/FactorRequest.py
okta/models/factor/FactorUpdateRequest.py
okta/models/factor/FactorVerificationResponse.py
okta/models/factor/OrgAuthFactor.py
okta/models/factor/Question.py
okta/models/factor/Verification.py
okta/models/factor/__init__.py
okta/models/session/Credentials.py
okta/models/session/Session.py
okta/models/session/__init__.py
okta/models/user/ActivationResponse.py
okta/models/user/AppLinks.py
okta/models/user/ChangePasswordRequest.py
okta/models/user/ChangeRecoveryQuestionRequest.py
okta/models/user/LoginCredentials.py
okta/models/user/Password.py
okta_api.egg-info/PKG-INFO
okta_api.egg-info/SOURCES.txt
okta_api.egg-info/dependency_links.txt
okta_api.egg-info/requires.txt
okta_api.egg-info/top_level.txt